youconfigme/__init__.py
youconfigme/getpass.py
youconfigme/youconfigme.py
youconfigme-1.0.0.dist-info/LICENSE
youconfigme-1.0.0.dist-info/METADATA
youconfigme-1.0.0.dist-info/WHEEL
youconfigme-1.0.0.dist-info/top_level.txt
youconfigme-1.0.0.dist-info/RECORD
