Metadata-Version: 2.1
Name: youconfigme
Version: 1.0.0
Summary: YouConfigMe helps you manage config in a pythonic way
Home-page: https://github.com/crossnox/YouConfigMe
Author: CrossNox
License: UNKNOWN
Platform: UNKNOWN
Classifier: Programming Language :: Python :: 3
Requires-Dist: toml
Provides-Extra: dev
Requires-Dist: pre-commit; extra == "dev"
Requires-Dist: mypy; extra == "dev"
Requires-Dist: flake8; extra == "dev"
Requires-Dist: isort; extra == "dev"
Requires-Dist: black; extra == "dev"
Requires-Dist: pylint; extra == "dev"
Requires-Dist: bump; extra == "dev"
Requires-Dist: nox; extra == "dev"
Requires-Dist: types-toml; extra == "dev"
Provides-Extra: test
Requires-Dist: pytest; extra == "test"
